setup.py
pyio/__init__.py
pyio.egg-info/PKG-INFO
pyio.egg-info/SOURCES.txt
pyio.egg-info/dependency_links.txt
pyio.egg-info/top_level.txt
pyio/io/LineStream.py
pyio/io/StreamWatcher.py
pyio/io/__init__.py
pyio/process/Process.py
pyio/process/ProcessManager.py
pyio/process/__init__.py