Metadata-Version: 1.0
Name: pyio
Version: 0.1.1
Summary: pyio
Home-page: https://github.com/theojulienne/pyio
Author: Theo Julienne
Author-email: theo.julienne+pyio@gmail
License: MIT
Platform: any
